.DS_Store
naplib/__init__.py
naplib/data.py
naplib/array_ops/__init__.py
naplib/array_ops/center_of_mass_functions.py
naplib/array_ops/operations.py
naplib/encoding/__init__.py
naplib/encoding/trf.py
naplib/features/__init__.py
naplib/features/aligner.py
naplib/features/alignment_extras.py
naplib/features/auditory_spectrogram.py
naplib/features/cochba.mat
naplib/features/eng.yaml
naplib/features/peak_rate.py
naplib/features/resample.sh
naplib/features/sort.py
naplib/features/test.wav
naplib/features/prosodylab_aligner/LICENSE
naplib/features/prosodylab_aligner/__init__.py
naplib/features/prosodylab_aligner/aligner.py
naplib/features/prosodylab_aligner/archive.py
naplib/features/prosodylab_aligner/corpus.py
naplib/features/prosodylab_aligner/eng.dict
naplib/features/prosodylab_aligner/eng.zip
naplib/features/prosodylab_aligner/prondict.py
naplib/features/prosodylab_aligner/run_aligner.py
naplib/features/prosodylab_aligner/utilities.py
naplib/features/prosodylab_aligner/wavfile.py
naplib/io/__init__.py
naplib/io/fileio.py
naplib/io/load_bids.py
naplib/io/load_cnd.py
naplib/io/load_edf.py
naplib/io/load_nwb.py
naplib/io/load_sample.py
naplib/io/load_tdt.py
naplib/io/load_wav_dir.py
naplib/io/read_htk.py
naplib/io/sample_data/demo_data.mat
naplib/localization/__init__.py
naplib/localization/coordinate_conversions.py
naplib/localization/freesurfer.py
naplib/model_selection/__init__.py
naplib/model_selection/model_selection.py
naplib/naplab/__init__.py
naplib/naplab/alignment.py
naplib/naplab/process_ieeg.py
naplib/preprocessing/__init__.py
naplib/preprocessing/filter.py
naplib/preprocessing/filter_hilbert.py
naplib/preprocessing/preprocess.py
naplib/preprocessing/rereference.py
naplib/segmentation/__init__.py
naplib/segmentation/segmentation.py
naplib/stats/__init__.py
naplib/stats/encoding.py
naplib/stats/mixedeffectsmodel.py
naplib/stats/pvalues.py
naplib/stats/responsive_ttest.py
naplib/stats/ttest.py
naplib/utils/__init__.py
naplib/utils/argchecking.py
naplib-2.6.0.dist-info/LICENSE
naplib-2.6.0.dist-info/METADATA
naplib-2.6.0.dist-info/WHEEL
naplib-2.6.0.dist-info/top_level.txt
naplib-2.6.0.dist-info/RECORD
