Metadata-Version: 2.1
Name: naplib
Version: 2.6.0
Summary: Tools and functions for neural data processing and analysis in python
Home-page: https://github.com/naplab/naplib-python
Author: Gavin Mischler, Vinay Raghavan, Menoua Keshishian
Maintainer: Gavin Mischler
Maintainer-email: gm2944@columbia.edu
License: MIT
Project-URL: Source, https://github.com/naplab/naplib-python
Project-URL: Tracker, https://github.com/naplab/naplib-python/issues/
Classifier: Development Status :: 3 - Alpha
Classifier: Intended Audience :: Science/Research
Classifier: Topic :: Scientific/Engineering :: Mathematics
Classifier: License :: OSI Approved :: MIT License
Classifier: Programming Language :: Python :: 3
Classifier: Programming Language :: Python :: 3.8
Classifier: Programming Language :: Python :: 3.9
Classifier: Programming Language :: Python :: 3.10
Requires-Python: >=3.8
License-File: LICENSE
Requires-Dist: matplotlib >=3.1.0
Requires-Dist: numpy <2.0,>=1.15.0
Requires-Dist: scipy >=1.5.0
Requires-Dist: pandas >=1.0.0
Requires-Dist: statsmodels >=0.13.0
Requires-Dist: hdf5storage >=0.1.1
Requires-Dist: seaborn >=0.12.0
Requires-Dist: pyyaml
Requires-Dist: TextGrid
Requires-Dist: scikit-learn
Requires-Dist: joblib
Requires-Dist: mne
Requires-Dist: h5py
Requires-Dist: patsy
Requires-Dist: tdt >=0.5.0
Requires-Dist: packaging
Requires-Dist: plotly >=5.0.0
Requires-Dist: nibabel >=5.0.0
Requires-Dist: scikit-spatial >=5.0.0
Requires-Dist: gdist >=2.0.0
